mongotq/__init__.py
mongotq/anomalies.py
mongotq/interface.py
mongotq/task.py
mongotq/task_queue.py
mongo_taskqueue-0.2.4.dist-info/LICENSE
mongo_taskqueue-0.2.4.dist-info/METADATA
mongo_taskqueue-0.2.4.dist-info/WHEEL
mongo_taskqueue-0.2.4.dist-info/top_level.txt
mongo_taskqueue-0.2.4.dist-info/RECORD
